[
    {
        "settings": [ "master" ],
        "shaker":{
            },
        "specs": {
            "pnm": {
                "type": "PNM",
                "config": {
                    "children": {
                        "lightbox": {
                            "type": "lightbox"
                        },
                        "grid": {
                            "type": "grid"
                        }
                    }
                }
            },
            "frame": {
                "type": "SearchHTMLFrame",
                "config": {
                    "title": "Photos Near Me",
                    "deploy": true,
                    "child" : {
                        "base": "pnm"
                    }
                }
            }
        },
        "yui": {
            "config": {
                "bootstrap": true,
                "combine": false,
                "filter": "debug",
                "logExclude": {
                    "attribute": true,
                    "event": true,
                    "node": true,
                    "Selector": true,
                    "base": true,
                    "widget": true,
                    "Plugin": true
                }
            },
            "dependencyCalculations": "precomputed"
        },
        "staticHandling": {
            "appName": "i",
            "prefix": ""
        }
    },
    {
        "settings": [ "environment:development" ],
        "staticHandling": {
            "forceUpdate": true
        }
    },
    {
        "settings": [ "environment:test" ],
        "shaker":{
            "task": "local"
        }
    }
]
